AUTHORS
CHANGES
LICENSE.txt
MANIFEST.in
README.rst
__editobj3__.py
__init__.py
application-x-songwrite.xml
canvas.py
globdef.py
main.py
midi.py
model.py
pipe.py
player.py
setup.cfg
setup.py
songwrite3
songwrite3.desktop
stemml.py
./__editobj3__.py
./__init__.py
./canvas.py
./globdef.py
./main.py
./midi.py
./model.py
./pipe.py
./player.py
./stemml.py
./data/Sans titre.xcf
./data/accordion.png
./data/bar.png
./data/clef_de_fa.png
./data/clef_de_sol.png
./data/document-new.svg
./data/document-open.svg
./data/document-print.svg
./data/document-properties.svg
./data/document-save.svg
./data/edit-paste.svg
./data/edit-redo.svg
./data/edit-select-all.svg
./data/edit-undo.svg
./data/effet_accent.png
./data/effet_appoggiatura.png
./data/effet_bend.png
./data/effet_breath.png
./data/effet_dead.png
./data/effet_down.png
./data/effet_down_thumb.png
./data/effet_fermata.png
./data/effet_harmonic.png
./data/effet_link.png
./data/effet_roll.png
./data/effet_slide.png
./data/effet_tremolo.png
./data/effet_up.png
./data/flute.png
./data/flute_irlandaise.png
./data/go-down.svg
./data/go-up.svg
./data/guitar.png
./data/help-about.svg
./data/help-contents.svg
./data/index.theme
./data/instruments.png
./data/list-add.svg
./data/list-remove.svg
./data/lyre.png
./data/lyrics.png
./data/media-playback-start.svg
./data/media-playback-stop.svg
./data/no_icon.png
./data/note_.xcf
./data/note_12.png
./data/note_128.png
./data/note_144.png
./data/note_16.png
./data/note_18.png
./data/note_192.png
./data/note_24.png
./data/note_256.png
./data/note_288.png
./data/note_32.png
./data/note_36.png
./data/note_384.png
./data/note_48.png
./data/note_576.png
./data/note_64.png
./data/note_72.png
./data/note_8.png
./data/note_96.png
./data/piano.png
./data/playlist.png
./data/preferences-other.svg
./data/rest_12.png
./data/rest_24.png
./data/rest_48.png
./data/rest_96.png
./data/son_accordeon.mid
./data/son_chant.mid
./data/son_flute.mid
./data/son_guitare.mid
./data/son_lyre.mid
./data/song.png
Songwrite3.egg-info/PKG-INFO
Songwrite3.egg-info/SOURCES.txt
Songwrite3.egg-info/dependency_links.txt
Songwrite3.egg-info/requires.txt
Songwrite3.egg-info/top_level.txt
