Metadata-Version: 2.1
Name: Songwrite3
Version: 0.2
Summary: Tablature editor with Python 3, Qt 5, EditObj 3, and Timidity
Home-page: http://www.lesfleursdunormal.fr/static/informatique/songwrite/index_en.html
Author: Lamy Jean-Baptiste
Author-email: jibalamy@free.fr
License: GPL
Platform: Unix
Platform: Linux
Classifier: Development Status :: 4 - Beta
Classifier: Environment :: X11 Applications
Classifier: Environment :: X11 Applications :: Qt
Classifier: Intended Audience :: End Users/Desktop
Classifier: License :: OSI Approved :: GNU General Public License v3 or later (GPLv3+)
Classifier: Natural Language :: French
Classifier: Natural Language :: English
Classifier: Operating System :: Unix
Classifier: Operating System :: POSIX :: Linux
Classifier: Programming Language :: Python :: 3
Classifier: Programming Language :: Python :: 3 :: Only
Classifier: Programming Language :: Python :: 3.5
Classifier: Topic :: Artistic Software
Classifier: Topic :: Multimedia :: Sound/Audio
Classifier: Topic :: Multimedia :: Sound/Audio :: Editors
Classifier: Topic :: Multimedia :: Sound/Audio :: MIDI
License-File: LICENSE.txt
License-File: AUTHORS
